[ 
 {
    "bank": "LTCC::clusters",
    "group": 21622,
    "info": "reconstructed clusters from the LTCC",
    "items": [
       {"name":"id",          "id":1, "type":"int16",  "info":"id of the cluster"},
       {"name":"status",      "id":2, "type":"int8",  "info":"good (1) or bad (0)"},       
       {"name":"sector",      "id":3, "type":"int8",   "info":"sector of LTCC"},
       {"name":"segment",     "id":4, "type":"int16",  "info":"weighted central cluster segment"},
       {"name":"x",           "id":5, "type":"float", "info":"crude cluster center (cm)"},
       {"name":"y",           "id":6, "type":"float", "info":"crude cluster center (cm)"},
       {"name":"z",           "id":7, "type":"float", "info":"crude cluster center (cm)"},
       {"name":"nphe",        "id":8, "type":"float", "info":"number of photo-electrons"},
       {"name":"time",        "id":9, "type":"float", "info":"cluster time"},
       {"name":"nHits",      "id":10, "type":"int16", "info":"number of hits in this cluster"},
       {"name":"minTheta",   "id":11, "type":"float", "info":"minimum theta angle of the cluster (deg)"},
       {"name":"maxTheta",   "id":12, "type":"float", "info":"maximum theta angle of the cluster (deg)"},
       {"name":"minPhi",     "id":13, "type":"float", "info":"minimum phi angle of the cluster (deg)"},
       {"name":"maxPhi",     "id":14, "type":"float", "info":"maximum phi angle of the cluster (deg)"}
    ]
  }
]
